setup.py
flaskrestframework.egg-info/PKG-INFO
flaskrestframework.egg-info/SOURCES.txt
flaskrestframework.egg-info/dependency_links.txt
flaskrestframework.egg-info/not-zip-safe
flaskrestframework.egg-info/requires.txt
flaskrestframework.egg-info/top_level.txt
rest_framework_flask/__init__.py
rest_framework_flask/api_setting.py
rest_framework_flask/decorators.py
rest_framework_flask/exceptions.py
rest_framework_flask/middleware.py
rest_framework_flask/permissions.py
rest_framework_flask/status.py
rest_framework_flask/utils.py
rest_framework_flask/validator.py
rest_framework_flask/versioning.py
rest_framework_flask/views.py
rest_framework_flask/schemas/__init__.py
rest_framework_flask/schemas/fields.py
rest_framework_flask/schemas/schema.py