Metadata-Version: 1.0
Name: flaskrestframework
Version: 0.1.4
Summary: Web APIs for Flask, made easy.
Home-page: UNKNOWN
Author: quxl
Author-email: quxl@snbway.com
License: MIT
Platform: UNKNOWN
